setup.py
lib/pycat/__init__.py
lib/pycat/pycat.py
lib/wf_pycat.egg-info/PKG-INFO
lib/wf_pycat.egg-info/SOURCES.txt
lib/wf_pycat.egg-info/dependency_links.txt
lib/wf_pycat.egg-info/pbr.json
lib/wf_pycat.egg-info/requires.txt
lib/wf_pycat.egg-info/top_level.txt