Metadata-Version: 1.1
Name: wf-pycat
Version: 0.0.1
Summary: Runner Variant of Netcat
Home-page: https://github.com/CenturylinkTechnology/wf-pycat.git
Author: Mark Ramach
Author-email: mark.ramach@centurylink.com
License: UNKNOWN
Download-URL: https://github.com/CenturylinkTechnology/wf-pycat
Platform: UNKNOWN
